<?xml version="1.0" encoding="utf-8"?>
<diff>
	<!-- =============== -->
	<!-- Duration Change -->
	<!-- =============== -->
	<!-- Teleportation	-->
	<!-- Teleportation rank 1 is really important so I'll consider the research is already almost complete when we discover the PHQ -->
	<replace sel="/wares/ware[@id='research_teleportation']/research/@time">900</replace>
	<replace sel="/wares/ware[@id='research_teleportation_range_01']/research/@time">1800</replace>
	<replace sel="/wares/ware[@id='research_teleportation_range_02']/research/@time">3600</replace>
	<replace sel="/wares/ware[@id='research_teleportation_range_03']/research/@time">7200</replace>
	
	<!-- Module Hack -->
	<replace sel="/wares/ware[@id='research_module_dock']/research/@time">900</replace>
	<replace sel="/wares/ware[@id='research_module_production']/research/@time">900</replace>
	<replace sel="/wares/ware[@id='research_module_storage']/research/@time">900</replace>
	
	<replace sel="/wares/ware[@id='research_module_defence']/research/@time">1800</replace>
	<replace sel="/wares/ware[@id='research_module_habitation']/research/@time">1800</replace>
	
	<!-- Mods -->
	<replace sel="/wares/ware[@id='research_mod_engine_mk1']/research/@time">1800</replace>
	<replace sel="/wares/ware[@id='research_mod_shield_mk1']/research/@time">1800</replace>
	<replace sel="/wares/ware[@id='research_mod_ship_mk1']/research/@time">1800</replace>
	<replace sel="/wares/ware[@id='research_mod_weapon_mk1']/research/@time">1800</replace>
	
	<replace sel="/wares/ware[@id='research_mod_engine_mk2']/research/@time">3600</replace>
	<replace sel="/wares/ware[@id='research_mod_shield_mk2']/research/@time">3600</replace>
	<replace sel="/wares/ware[@id='research_mod_ship_mk2']/research/@time">3600</replace>
	<replace sel="/wares/ware[@id='research_mod_weapon_mk2']/research/@time">3600</replace>
	
	<replace sel="/wares/ware[@id='research_mod_engine_mk3']/research/@time">7200</replace>
	<replace sel="/wares/ware[@id='research_mod_shield_mk3']/research/@time">7200</replace>
	<replace sel="/wares/ware[@id='research_mod_ship_mk3']/research/@time">7200</replace>
	<replace sel="/wares/ware[@id='research_mod_weapon_mk3']/research/@time">7200</replace>
	
	<!-- ======================= -->
	<!-- Adds Wares for Research -->
	<!-- ======================= -->
	<!-- Teleportation	-->
	<add sel="/wares/ware[@id='research_teleportation']/research">
			<primary>
				<ware ware="energycells" amount="1350" />
				<ware ware="smartchips" amount="270" />
				<ware ware="antimatterconverters" amount="135" />
				<ware ware="fieldcoils" amount="90" />
				<ware ware="advancedelectronics" amount="45" />
			</primary>
	</add>
	<add sel="/wares/ware[@id='research_teleportation_range_01']/research">
			<primary>
				<ware ware="energycells" amount="28404" />
				<ware ware="smartchips" amount="5681" />
				<ware ware="antimatterconverters" amount="2840" />
				<ware ware="fieldcoils" amount="1894" />
				<ware ware="advancedelectronics" amount="947" />
			</primary>
	</add>
	<add sel="/wares/ware[@id='research_teleportation_range_02']/research">
			<primary>
				<ware ware="energycells" amount="110160" />
				<ware ware="smartchips" amount="22032" />
				<ware ware="antimatterconverters" amount="11016" />
				<ware ware="fieldcoils" amount="7344" />
				<ware ware="advancedelectronics" amount="3672" />
			</primary>
	</add>
	<add sel="/wares/ware[@id='research_teleportation_range_03']/research">
			<primary>
				<ware ware="energycells" amount="496800" />
				<ware ware="smartchips" amount="99360" />
				<ware ware="antimatterconverters" amount="49680" />
				<ware ware="fieldcoils" amount="33120" />
				<ware ware="advancedelectronics" amount="16560" />
			</primary>
	</add>
	<!-- Module Hack -->
	<add sel="/wares/ware[@id='research_module_dock']/research">
			<primary>
				<ware ware="energycells" amount="28404" />
				<ware ware="advancedelectronics" amount="947" />
			</primary>
	</add>
	<add sel="/wares/ware[@id='research_module_production']/research">
			<primary>
				<ware ware="energycells" amount="28404" />
				<ware ware="advancedelectronics" amount="947" />
			</primary>
	</add>
	<add sel="/wares/ware[@id='research_module_storage']/research">
			<primary>
				<ware ware="energycells" amount="28404" />
				<ware ware="advancedelectronics" amount="947" />
			</primary>
	</add>
	<add sel="/wares/ware[@id='research_module_defence']/research">
			<primary>
				<ware ware="energycells" amount="110160" />
				<ware ware="advancedelectronics" amount="3672" />
			</primary>
	</add>
	<add sel="/wares/ware[@id='research_module_habitation']/research">
			<primary>
				<ware ware="energycells" amount="110160" />
				<ware ware="advancedelectronics" amount="3672" />
			</primary>
	</add>
	<!-- Mods -->
	<add sel="/wares/ware[@id='research_mod_engine_mk1']/research">
			<primary>
				<ware ware="energycells" amount="28404" />
				<ware ware="smartchips" amount="5681" />
				<ware ware="antimatterconverters" amount="2840" />
				<ware ware="fieldcoils" amount="1894" />
				<ware ware="advancedelectronics" amount="947" />
				<ware ware="engineparts" amount="947" />
			</primary>
	</add>
	<add sel="/wares/ware[@id='research_mod_shield_mk1']/research">
			<primary>
				<ware ware="energycells" amount="28404" />
				<ware ware="smartchips" amount="5681" />
				<ware ware="antimatterconverters" amount="2840" />
				<ware ware="fieldcoils" amount="1894" />
				<ware ware="advancedelectronics" amount="947" />
				<ware ware="shieldcomponents" amount="2840" />
			</primary>
	</add>
	<add sel="/wares/ware[@id='research_mod_ship_mk1']/research">
			<primary>
				<ware ware="energycells" amount="28404" />
				<ware ware="smartchips" amount="5681" />
				<ware ware="antimatterconverters" amount="2840" />
				<ware ware="fieldcoils" amount="1894" />
				<ware ware="advancedelectronics" amount="947" />
				<ware ware="hullparts" amount="1136" />
			</primary>
	</add>
	<add sel="/wares/ware[@id='research_mod_weapon_mk1']/research">
			<primary>
				<ware ware="energycells" amount="28404" />
				<ware ware="smartchips" amount="5681" />
				<ware ware="antimatterconverters" amount="2840" />
				<ware ware="fieldcoils" amount="1894" />
				<ware ware="advancedelectronics" amount="947" />
				<ware ware="weaponcomponents" amount="1420" />
			</primary>
	</add>
	<!-- Lv. 2 -->
	<add sel="/wares/ware[@id='research_mod_engine_mk2']/research">
			<primary>
				<ware ware="energycells" amount="110160" />
				<ware ware="smartchips" amount="22032" />
				<ware ware="antimatterconverters" amount="11016" />
				<ware ware="fieldcoils" amount="7344" />
				<ware ware="advancedelectronics" amount="3672" />
				<ware ware="engineparts" amount="3672" />
			</primary>
	</add>
	<add sel="/wares/ware[@id='research_mod_shield_mk2']/research">
			<primary>
				<ware ware="energycells" amount="110160" />
				<ware ware="smartchips" amount="22032" />
				<ware ware="antimatterconverters" amount="11016" />
				<ware ware="fieldcoils" amount="7344" />
				<ware ware="advancedelectronics" amount="3672" />
				<ware ware="shieldcomponents" amount="11016" />
			</primary>
	</add>
	<add sel="/wares/ware[@id='research_mod_ship_mk2']/research">
			<primary>
				<ware ware="energycells" amount="110160" />
				<ware ware="smartchips" amount="22032" />
				<ware ware="antimatterconverters" amount="11016" />
				<ware ware="fieldcoils" amount="7344" />
				<ware ware="advancedelectronics" amount="3672" />
				<ware ware="hullparts" amount="4406" />
			</primary>
	</add>
	<add sel="/wares/ware[@id='research_mod_weapon_mk2']/research">
			<primary>
				<ware ware="energycells" amount="110160" />
				<ware ware="smartchips" amount="22032" />
				<ware ware="antimatterconverters" amount="11016" />
				<ware ware="fieldcoils" amount="7344" />
				<ware ware="advancedelectronics" amount="3672" />
				<ware ware="weaponcomponents" amount="5508" />
			</primary>
	</add>
	<!-- Lv3. -->
	<add sel="/wares/ware[@id='research_mod_engine_mk3']/research">
			<primary>
				<ware ware="energycells" amount="496800" />
				<ware ware="smartchips" amount="99360" />
				<ware ware="antimatterconverters" amount="49680" />
				<ware ware="fieldcoils" amount="33120" />
				<ware ware="advancedelectronics" amount="16560" />
				<ware ware="engineparts" amount="16560" />
			</primary>
	</add>
	<add sel="/wares/ware[@id='research_mod_shield_mk3']/research">
			<primary>
				<ware ware="energycells" amount="496800" />
				<ware ware="smartchips" amount="99360" />
				<ware ware="antimatterconverters" amount="49680" />
				<ware ware="fieldcoils" amount="33120" />
				<ware ware="advancedelectronics" amount="16560" />
				<ware ware="shieldcomponents" amount="49680" />
			</primary>
	</add>
	<add sel="/wares/ware[@id='research_mod_ship_mk3']/research">
			<primary>
				<ware ware="energycells" amount="496800" />
				<ware ware="smartchips" amount="99360" />
				<ware ware="antimatterconverters" amount="49680" />
				<ware ware="fieldcoils" amount="33120" />
				<ware ware="advancedelectronics" amount="16560" />
				<ware ware="hullparts" amount="19872" />
			</primary>
	</add>
	<add sel="/wares/ware[@id='research_mod_weapon_mk3']/research">
			<primary>
				<ware ware="energycells" amount="496800" />
				<ware ware="smartchips" amount="99360" />
				<ware ware="antimatterconverters" amount="49680" />
				<ware ware="fieldcoils" amount="33120" />
				<ware ware="advancedelectronics" amount="16560" />
				<ware ware="weaponcomponents" amount="24840" />
			</primary>
	</add>
</diff>